pollenflug/lib/__init__.py
pollenflug/lib/color.py
pollenflug/lib/consts.py
pollenflug/lib/functions.py
pollenflug/pollenflug.py
pollenflug-0.3.3.dist-info/LICENSE
pollenflug-0.3.3.dist-info/METADATA
pollenflug-0.3.3.dist-info/WHEEL
pollenflug-0.3.3.dist-info/entry_points.txt
pollenflug-0.3.3.dist-info/RECORD
