Metadata-Version: 2.3
Name: pollenflug
Version: 0.3.3
Summary: CLI allergy forecast tool
License: GGPL-3.0-or-later
Author: Bader Zaidan
Author-email: python@zaidan.tech
Requires-Python: >=3.8,<4
Classifier: Environment :: Console
Classifier: License :: OSI Approved :: GNU General Public License v3 (GPLv3)
Classifier: License :: Other/Proprietary License
Classifier: Natural Language :: English
Classifier: Natural Language :: German
Classifier: Operating System :: OS Independent
Classifier: Programming Language :: Python
Classifier: Programming Language :: Python :: 3
Classifier: Programming Language :: Python :: 3.8
Classifier: Programming Language :: Python :: 3.9
Classifier: Programming Language :: Python :: 3.10
Classifier: Programming Language :: Python :: 3.11
Classifier: Programming Language :: Python :: 3.12
Classifier: Programming Language :: Python :: 3.13
Requires-Dist: requests (>=2.31.0,<3.0.0)
Project-URL: Homepage, https://github.com/BaderSZ/pollenflug
Project-URL: Repository, https://github.com/BaderSZ/pollenflug
